<?xml version="1.0" encoding="UTF-8"?>

<!-- generated on 11/21/21 21:05:14 by Eclipse SUMO GUI Version 1.6.0
<configuration xmlns:xsi="http://www.w3.org/2001/XMLSchema-instance" xsi:noNamespaceSchemaLocation="http://sumo.dlr.de/xsd/sumoConfiguration.xsd">

    <input>
        <net-file value="C:\Users\744\Desktop\atsc_deeprl\sumo_file\VSL\net1019.net.xml"/>
        <route-files value="C:\Users\744\Desktop\atsc_deeprl\sumo_file\VSL\1019.rou.xml"/>
        <additional-files value="C:\Users\744\Desktop\atsc_deeprl\sumo_file\VSL\add.add.xml"/>
    </input>

</configuration>
-->

<detector xmlns:xsi="http://www.w3.org/2001/XMLSchema-instance" xsi:noNamespaceSchemaLocation="http://sumo.dlr.de/xsd/det_e1_file.xsd">
    <interval begin="0.00" end="10.00" id="det_L1_0" nVehContrib="0" flow="0.00" occupancy="0.00" speed="-1.00" harmonicMeanSpeed="-1.00" length="-1.00" nVehEntered="0"/>
</detector>
